MANIFEST.in
README
RELEASE-VERSION
ez_setup.py
setup.cfg
setup.py
version.py
buildout/__init__.py
buildout/python_libevent.py
buildout.python_libevent.egg-info/PKG-INFO
buildout.python_libevent.egg-info/SOURCES.txt
buildout.python_libevent.egg-info/dependency_links.txt
buildout.python_libevent.egg-info/entry_points.txt
buildout.python_libevent.egg-info/namespace_packages.txt
buildout.python_libevent.egg-info/requires.txt
buildout.python_libevent.egg-info/top_level.txt