Metadata-Version: 1.0
Name: buildout.python_libevent
Version: 0.9.1
Summary: Buildout recipe for python-libevent
Home-page: http://www.joachim-bauch.de/projects/python-libevent/
Author: Joachim Bauch
Author-email: mail@joachim-bauch.de
License: UNKNOWN
Download-URL: http://pypi.python.org/pypi/buildout.python_libevent/
Keywords: buildout recipe libevent
Platform: UNKNOWN
